rdf/__init__.py
rdf/admin.py
rdf/apps.py
rdf/baseclasses.py
rdf/conftest.py
rdf/migrations.py
rdf/migrations_test.py
rdf/ns.py
rdf/parsers.py
rdf/parsers_test.py
rdf/renderers.py
rdf/renderers_test.py
rdf/utils.py
rdf/utils_test.py
rdf/views.py
rdf/management/__init__.py
rdf/management/commands/__init__.py
rdf/management/commands/_rdfmigrate_test.py
rdf/management/commands/rdfmigrate.py
sparql/__init__.py
sparql/apps.py
sparql/conftest.py
sparql/constants.py
sparql/exceptions.py
sparql/negotiation.py
sparql/renderers.py
sparql/utils.py
sparql/utils_test.py
sparql/views.py
sparql/views_test.py
sparql/migrations/__init__.py
sparql/test_app/__init__.py
sparql/test_app/constants.py
sparql/test_app/graphs.py
sparql/test_app/urls.py
sparql/test_app/views.py
restframework_rdf-1.2.0.dist-info/LICENSE
restframework_rdf-1.2.0.dist-info/METADATA
restframework_rdf-1.2.0.dist-info/WHEEL
restframework_rdf-1.2.0.dist-info/top_level.txt
restframework_rdf-1.2.0.dist-info/RECORD
