Metadata-Version: 2.1
Name: restframework-rdf
Version: 1.2.0
Summary: A Django app for integration between django rest framework and RDF
Home-page: https://github.com/UUDigitalHumanitieslab/restframework-rdf
Author: Utrecht University, Centre for Digital Humanities - Research Software Lab
Author-email: cdh@uu.nl
License: BSD-3
Classifier: Environment :: Web Environment
Classifier: Framework :: Django
Classifier: Framework :: Django :: 3.2
Classifier: Intended Audience :: Developers
Classifier: License :: OSI Approved :: BSD License
Classifier: Operating System :: OS Independent
Classifier: Programming Language :: Python
Classifier: Programming Language :: Python :: 3
Classifier: Programming Language :: Python :: 3 :: Only
Classifier: Programming Language :: Python :: 3.8
Classifier: Programming Language :: Python :: 3.9
Classifier: Topic :: Internet :: WWW/HTTP
Classifier: Topic :: Internet :: WWW/HTTP :: Dynamic Content
Requires-Python: >=3.8
License-File: LICENSE
Requires-Dist: django >=3.2
Requires-Dist: djangorestframework
Requires-Dist: rdflib >6
